{
  "template": "https://gitlab.kit.edu/FObersteiner/python-template/",
  "commit": "1edf2a6e9d4909e3474e767710f6e272a679be9f",
  "checkout": null,
  "context": {
    "cookiecutter": {
      "author": "Florian Obersteiner",
      "email": "f.obersteiner@kit.edu",
      "organization": "KIT",
      "year": "2025",
      "license": "GPL-3.0-or-later",
      "project_name": "pyFuppes",
      "project_slug": "pyfuppes",
      "project_description": "A collection of tools in Python",
      "_template": "https://gitlab.kit.edu/FObersteiner/python-template/",
      "_commit": "1edf2a6e9d4909e3474e767710f6e272a679be9f"
    }
  },
  "directory": null
}
