[
  {
    "Continent": "Global",
    "Country": "Global",
    "City": "not defined",
    "ISO-3166-1 ALPHA-2": "GLO",
    "REMIND Region": "GLO",
    "Sector": "Transport",
    "Type": "transport, freight, lorry >32 metric ton, EURO6, hazardous, foreground",
    "Costs per unit [USD/unit]": 0.122872340425532,
    "Unit": "tkm",
    "Base Year": 2021,
    "Costs per unit [USD/unit] Reference year": 0.130637477995646,
    "Reference year": 2023,
    "Costs per unit [USD/unit] Future": 0.164218678425936,
    "SSP2-Base year": 2035,
    "Identifier": "transport",
    "Years": 0,
    "Description": "This dataset describes the average price per tkm for transportation of a harzdous good by lorry\nAssumption: Transport of containers on an LVZ\nLocation: Global\nReference period: 2021\nReference: Panteia",
    "Reference": "van der Meulen et al. 2023",
    "Comment": "factor of 5% considered for the transport of hazardous goods",
    "Code": "f59394ab74891208a8122f314a8d6001"
  },
  {
    "Continent": "Global",
    "Country": "Global",
    "City": "not defined",
    "ISO-3166-1 ALPHA-2": "GLO",
    "REMIND Region": "GLO",
    "Sector": "Transport",
    "Type": "transport, freight, lorry >32 metric ton, EURO6, non-hazardous, foreground",
    "Costs per unit [USD/unit]": 0.117021276595745,
    "Unit": "tkm",
    "Base Year": 2021,
    "Costs per unit [USD/unit] Reference year": 0.124416645710139,
    "Reference year": 2023,
    "Costs per unit [USD/unit] Future": 0.156398741358034,
    "SSP2-Base year": 2035,
    "Identifier": "transport",
    "Years": 0,
    "Description": "This dataset describes the average price per tkm for transportation of a non-harzdous good by lorry\nAssumption: Transport of containers on an LVZ\nLocation: Global\nReference period: 2021\nReference: Panteia",
    "Reference": "van der Meulen et al. 2023",
    "Code": "f59394ab74891208a8122f314a8d6002"
  },
  {
    "Continent": "Global",
    "Country": "Global",
    "City": "not defined",
    "ISO-3166-1 ALPHA-2": "GLO",
    "REMIND Region": "GLO",
    "Sector": "Transport",
    "Type": "transport, freight, inland waterways, barge, hazardous, foreground",
    "Costs per unit [USD/unit]": 0.0310283687943262,
    "Unit": "tkm",
    "Base Year": 2021,
    "Costs per unit [USD/unit] Reference year": 0.0329892621201127,
    "Reference year": 2023,
    "Costs per unit [USD/unit] Future": 0.0414693632388728,
    "SSP2-Base year": 2035,
    "Identifier": "transport",
    "Years": 0,
    "Description": "This dataset describes the average price per tkm for transportation of a harzdous good by barge\nAssumption: Transport of containers on large ships\nLocation: Global\nReference period: 2021\nReference: Panteia",
    "Reference": "van der Meulen et al. 2023",
    "Comment": "factor of 5% considered for the transport of hazardous goods",
    "Code": "f59394ab74891208a8122f314a8d6003"
  },
  {
    "Continent": "Global",
    "Country": "Global",
    "City": "not defined",
    "ISO-3166-1 ALPHA-2": "GLO",
    "REMIND Region": "GLO",
    "Sector": "Transport",
    "Type": "transport, freight, inland waterways, barge, non-hazardous, foreground",
    "Costs per unit [USD/unit]": 0.0295508274231678,
    "Unit": "tkm",
    "Base Year": 2021,
    "Costs per unit [USD/unit] Reference year": 0.0314183448762978,
    "Reference year": 2023,
    "Costs per unit [USD/unit] Future": 0.0394946316560693,
    "SSP2-Base year": 2035,
    "Identifier": "transport",
    "Years": 0,
    "Description": "This dataset describes the average price per tkm for transportation of a non-harzdous good by barge\nAssumption: Transport of containers on large ships\nLocation: Global\nReference period: 2021\nReference: Panteia",
    "Reference": "van der Meulen et al. 2023",
    "Code": "f59394ab74891208a8122f314a8d6004"
  },
  {
    "Continent": "Global",
    "Country": "Global",
    "City": "not defined",
    "ISO-3166-1 ALPHA-2": "GLO",
    "REMIND Region": "GLO",
    "Sector": "Transport",
    "Type": "transport, freight, sea, container ship, hazardous, foreground",
    "Costs per unit [USD/unit]": 0.00173758865248227,
    "Unit": "tkm",
    "Base Year": 2021,
    "Costs per unit [USD/unit] Reference year": 0.00184739867872631,
    "Reference year": 2023,
    "Costs per unit [USD/unit] Future": 0.00232228434137687,
    "SSP2-Base year": 2035,
    "Identifier": "transport",
    "Years": 0,
    "Description": "This dataset describes the average price per tkm for transportation of a harzdous good by container ship\nAssumption: Transport of containers on container ships\nLocation: Global\nReference period: 2021\nReference: Panteia",
    "Reference": "van der Meulen et al. 2023",
    "Comment": "factor of 5% considered for the transport of hazardous goods",
    "Code": "f59394ab74891208a8122f314a8d6005"
  },
  {
    "Continent": "Global",
    "Country": "Global",
    "City": "not defined",
    "ISO-3166-1 ALPHA-2": "GLO",
    "REMIND Region": "GLO",
    "Sector": "Transport",
    "Type": "transport, freight, sea, container ship, non-hazardous, foreground",
    "Costs per unit [USD/unit]": 0.0016548463356974,
    "Unit": "tkm",
    "Base Year": 2021,
    "Costs per unit [USD/unit] Reference year": 0.00175942731307268,
    "Reference year": 2023,
    "Costs per unit [USD/unit] Future": 0.00221169937273988,
    "SSP2-Base year": 2035,
    "Identifier": "transport",
    "Years": 0,
    "Description": "This dataset describes the average price per tkm for transportation of a non-harzdous good by container ships\nAssumption: Transport of containers on container ships ships\nLocation: Global\nReference period: 2021\nReference: Panteia",
    "Reference": "van der Meulen et al. 2023",
    "Code": "f59394ab74891208a8122f314a8d6006"
  },
  {
    "Continent": "Global",
    "Country": "Global",
    "City": "not defined",
    "ISO-3166-1 ALPHA-2": "GLO",
    "REMIND Region": "GLO",
    "Sector": "Transport",
    "Type": "transport, freight train, hazardous, foreground",
    "Costs per unit [USD/unit]": 0.0558510638297872,
    "Unit": "tkm",
    "Base Year": 2021,
    "Costs per unit [USD/unit] Reference year": 0.0593806718162029,
    "Reference year": 2023,
    "Costs per unit [USD/unit] Future": 0.0746448538299709,
    "SSP2-Base year": 2035,
    "Identifier": "transport",
    "Years": 0,
    "Description": "This dataset describes the average price per tkm for transportation of a harzdous good by train\nAssumption: Transport of containers on trains\nLocation: Global\nReference period: 2021\nReference: Panteia",
    "Reference": "van der Meulen et al. 2023",
    "Comment": "factor of 5% considered for the transport of hazardous goods",
    "Code": "f59394ab74891208a8122f314a8d6007"
  },
  {
    "Continent": "Global",
    "Country": "Global",
    "City": "not defined",
    "ISO-3166-1 ALPHA-2": "GLO",
    "REMIND Region": "GLO",
    "Sector": "Transport",
    "Type": "transport, freight train, non-hazardous, foreground",
    "Costs per unit [USD/unit]": 0.0531914893617021,
    "Unit": "tkm",
    "Base Year": 2021,
    "Costs per unit [USD/unit] Reference year": 0.0565530207773361,
    "Reference year": 2023,
    "Costs per unit [USD/unit] Future": 0.0710903369809247,
    "SSP2-Base year": 2035,
    "Identifier": "transport",
    "Years": 0,
    "Description": "This dataset describes the average price per tkm for transportation of a non-harzdous good by trains\nAssumption: Transport of containers on trains\nLocation: Global\nReference period: 2021\nReference: Panteia",
    "Reference": "van der Meulen et al. 2023",
    "Code": "f59394ab74891208a8122f314a8d6008"
  },
  {
    "Continent": "Europe",
    "Country": "Germany",
    "City": "not defined",
    "ISO-3166-1 ALPHA-2": "DE",
    "REMIND Region": "EUR",
    "Sector": "Transport",
    "Type": "transport, freight, lorry >32 metric ton, EURO6, hazardous, foreground",
    "Costs per unit [USD/unit]": 0.122872340425532,
    "Unit": "tkm",
    "Base Year": 2021,
    "Costs per unit [USD/unit] Reference year": 0.125720620046085,
    "Reference year": 2023,
    "Costs per unit [USD/unit] Future": 0.142322313773962,
    "SSP2-Base year": 2035,
    "Identifier": "transport",
    "Years": 0,
    "Description": "This dataset describes the average price per tkm for transportation of a harzdous good by lorry\nAssumption: Transport of containers on an LVZ\nLocation: Germany\nReference period: 2021\nReference: Panteia",
    "Reference": "van der Meulen et al. 2023",
    "Comment": "factor of 5% considered for the transport of hazardous goods",
    "Code": "f59394ab74891208a8122f314a8d6009"
  },
  {
    "Continent": "Europe",
    "Country": "Germany",
    "City": "not defined",
    "ISO-3166-1 ALPHA-2": "DE",
    "REMIND Region": "EUR",
    "Sector": "Transport",
    "Type": "transport, freight, lorry >32 metric ton, EURO6, non-hazardous, foreground",
    "Costs per unit [USD/unit]": 0.117021276595745,
    "Unit": "tkm",
    "Base Year": 2021,
    "Costs per unit [USD/unit] Reference year": 0.119733923853414,
    "Reference year": 2023,
    "Costs per unit [USD/unit] Future": 0.135545060737107,
    "SSP2-Base year": 2035,
    "Identifier": "transport",
    "Years": 0,
    "Description": "This dataset describes the average price per tkm for transportation of a harzdous good by lorry\nAssumption: Transport of containers on an LVZ\nLocation: Germany\nReference period: 2021\nReference: Panteia",
    "Reference": "van der Meulen et al. 2023",
    "Code": "f59394ab74891208a8122f314a8d6010"
  },
  {
    "Continent": "Europe",
    "Country": "Germany",
    "City": "not defined",
    "ISO-3166-1 ALPHA-2": "DE",
    "REMIND Region": "EUR",
    "Sector": "Transport",
    "Type": "transport, freight, inland waterways, barge, hazardous, foreground",
    "Costs per unit [USD/unit]": 0.0310283687943262,
    "Unit": "tkm",
    "Base Year": 2021,
    "Costs per unit [USD/unit] Reference year": 0.0317476313247689,
    "Reference year": 2023,
    "Costs per unit [USD/unit] Future": 0.035939978225748,
    "SSP2-Base year": 2035,
    "Identifier": "transport",
    "Years": 0,
    "Description": "This dataset describes the average price per tkm for transportation of a harzdous good by lorry\nAssumption: Transport of containers on an LVZ\nLocation: Germany\nReference period: 2021\nReference: Panteia",
    "Reference": "van der Meulen et al. 2023",
    "Comment": "factor of 5% considered for the transport of hazardous goods",
    "Code": "f59394ab74891208a8122f314a8d6011"
  },
  {
    "Continent": "Europe",
    "Country": "Germany",
    "City": "not defined",
    "ISO-3166-1 ALPHA-2": "DE",
    "REMIND Region": "EUR",
    "Sector": "Transport",
    "Type": "transport, freight, inland waterways, barge, non-hazardous, foreground",
    "Costs per unit [USD/unit]": 0.0295508274231678,
    "Unit": "tkm",
    "Base Year": 2021,
    "Costs per unit [USD/unit] Reference year": 0.0302358393569228,
    "Reference year": 2023,
    "Costs per unit [USD/unit] Future": 0.0342285506911886,
    "SSP2-Base year": 2035,
    "Identifier": "transport",
    "Years": 0,
    "Description": "This dataset describes the average price per tkm for transportation of a harzdous good by lorry\nAssumption: Transport of containers on an LVZ\nLocation: Germany\nReference period: 2021\nReference: Panteia",
    "Reference": "van der Meulen et al. 2023",
    "Code": "f59394ab74891208a8122f314a8d6012"
  },
  {
    "Continent": "Europe",
    "Country": "Germany",
    "City": "not defined",
    "ISO-3166-1 ALPHA-2": "DE",
    "REMIND Region": "EUR",
    "Sector": "Transport",
    "Type": "transport, freight, sea, container ship, hazardous, foreground",
    "Costs per unit [USD/unit]": 0.00173758865248227,
    "Unit": "tkm",
    "Base Year": 2021,
    "Costs per unit [USD/unit] Reference year": 0.00177786735418706,
    "Reference year": 2023,
    "Costs per unit [USD/unit] Future": 0.00201263878064189,
    "SSP2-Base year": 2035,
    "Identifier": "transport",
    "Years": 0,
    "Description": "This dataset describes the average price per tkm for transportation of a harzdous good by lorry\nAssumption: Transport of containers on an LVZ\nLocation: Germany\nReference period: 2021\nReference: Panteia",
    "Reference": "van der Meulen et al. 2023",
    "Comment": "factor of 5% considered for the transport of hazardous goods",
    "Code": "f59394ab74891208a8122f314a8d6013"
  },
  {
    "Continent": "Europe",
    "Country": "Germany",
    "City": "not defined",
    "ISO-3166-1 ALPHA-2": "DE",
    "REMIND Region": "EUR",
    "Sector": "Transport",
    "Type": "transport, freight, sea, container ship, non-hazardous, foreground",
    "Costs per unit [USD/unit]": 0.0016548463356974,
    "Unit": "tkm",
    "Base Year": 2021,
    "Costs per unit [USD/unit] Reference year": 0.00169320700398768,
    "Reference year": 2023,
    "Costs per unit [USD/unit] Future": 0.00191679883870656,
    "SSP2-Base year": 2035,
    "Identifier": "transport",
    "Years": 0,
    "Description": "This dataset describes the average price per tkm for transportation of a harzdous good by lorry\nAssumption: Transport of containers on an LVZ\nLocation: Germany\nReference period: 2021\nReference: Panteia",
    "Reference": "van der Meulen et al. 2023",
    "Code": "f59394ab74891208a8122f314a8d6014"
  },
  {
    "Continent": "Europe",
    "Country": "Germany",
    "City": "not defined",
    "ISO-3166-1 ALPHA-2": "DE",
    "REMIND Region": "EUR",
    "Sector": "Transport",
    "Type": "transport, freight train, hazardous, foreground",
    "Costs per unit [USD/unit]": 0.0558510638297872,
    "Unit": "tkm",
    "Base Year": 2021,
    "Costs per unit [USD/unit] Reference year": 0.057145736384584,
    "Reference year": 2023,
    "Costs per unit [USD/unit] Future": 0.0646919608063464,
    "SSP2-Base year": 2035,
    "Identifier": "transport",
    "Years": 0,
    "Description": "This dataset describes the average price per tkm for transportation of a harzdous good by lorry\nAssumption: Transport of containers on an LVZ\nLocation: Germany\nReference period: 2021\nReference: Panteia",
    "Reference": "van der Meulen et al. 2023",
    "Comment": "factor of 5% considered for the transport of hazardous goods",
    "Code": "f59394ab74891208a8122f314a8d6015"
  },
  {
    "Continent": "Europe",
    "Country": "Germany",
    "City": "not defined",
    "ISO-3166-1 ALPHA-2": "DE",
    "REMIND Region": "EUR",
    "Sector": "Transport",
    "Type": "transport, freight train, non-hazardous, foreground",
    "Costs per unit [USD/unit]": 0.0531914893617021,
    "Unit": "tkm",
    "Base Year": 2021,
    "Costs per unit [USD/unit] Reference year": 0.054424510842461,
    "Reference year": 2023,
    "Costs per unit [USD/unit] Future": 0.0616113912441394,
    "SSP2-Base year": 2035,
    "Identifier": "transport",
    "Years": 0,
    "Description": "This dataset describes the average price per tkm for transportation of a harzdous good by lorry\nAssumption: Transport of containers on an LVZ\nLocation: Germany\nReference period: 2021\nReference: Panteia",
    "Reference": "van der Meulen et al. 2023",
    "Code": "f59394ab74891208a8122f314a8d6016"
  },
  {
    "Continent": "Europe",
    "Country": "Sweden",
    "City": "not defined",
    "ISO-3166-1 ALPHA-2": "SE",
    "REMIND Region": "EUR",
    "Sector": "Transport",
    "Type": "transport, freight, lorry >32 metric ton, EURO6, hazardous, foreground",
    "Costs per unit [USD/unit]": 0.122872340425532,
    "Unit": "tkm",
    "Base Year": 2021,
    "Costs per unit [USD/unit] Reference year": 0.125720620046085,
    "Reference year": 2023,
    "Costs per unit [USD/unit] Future": 0.142322313773962,
    "SSP2-Base year": 2035,
    "Identifier": "transport",
    "Years": 0,
    "Description": "This dataset describes the average price per tkm for transportation of a harzdous good by lorry\nAssumption: Transport of containers on an LVZ\nLocation: Sweden\nReference period: 2021\nReference: Panteia",
    "Reference": "van der Meulen et al. 2023",
    "Comment": "factor of 5% considered for the transport of hazardous goods",
    "Code": "f59394ab74891208a8122f314a8d6017"
  },
  {
    "Continent": "Europe",
    "Country": "Sweden",
    "City": "not defined",
    "ISO-3166-1 ALPHA-2": "SE",
    "REMIND Region": "EUR",
    "Sector": "Transport",
    "Type": "transport, freight, lorry >32 metric ton, EURO6, non-hazardous, foreground",
    "Costs per unit [USD/unit]": 0.117021276595745,
    "Unit": "tkm",
    "Base Year": 2021,
    "Costs per unit [USD/unit] Reference year": 0.119733923853414,
    "Reference year": 2023,
    "Costs per unit [USD/unit] Future": 0.135545060737107,
    "SSP2-Base year": 2035,
    "Identifier": "transport",
    "Years": 0,
    "Description": "This dataset describes the average price per tkm for transportation of a harzdous good by lorry\nAssumption: Transport of containers on an LVZ\nLocation: Sweden\nReference period: 2021\nReference: Panteia",
    "Reference": "van der Meulen et al. 2023",
    "Code": "f59394ab74891208a8122f314a8d6018"
  },
  {
    "Continent": "Europe",
    "Country": "Sweden",
    "City": "not defined",
    "ISO-3166-1 ALPHA-2": "SE",
    "REMIND Region": "EUR",
    "Sector": "Transport",
    "Type": "transport, freight, inland waterways, barge, hazardous, foreground",
    "Costs per unit [USD/unit]": 0.0310283687943262,
    "Unit": "tkm",
    "Base Year": 2021,
    "Costs per unit [USD/unit] Reference year": 0.0317476313247689,
    "Reference year": 2023,
    "Costs per unit [USD/unit] Future": 0.035939978225748,
    "SSP2-Base year": 2035,
    "Identifier": "transport",
    "Years": 0,
    "Description": "This dataset describes the average price per tkm for transportation of a harzdous good by lorry\nAssumption: Transport of containers on an LVZ\nLocation: Sweden\nReference period: 2021\nReference: Panteia",
    "Reference": "van der Meulen et al. 2023",
    "Comment": "factor of 5% considered for the transport of hazardous goods",
    "Code": "f59394ab74891208a8122f314a8d6019"
  },
  {
    "Continent": "Europe",
    "Country": "Sweden",
    "City": "not defined",
    "ISO-3166-1 ALPHA-2": "SE",
    "REMIND Region": "EUR",
    "Sector": "Transport",
    "Type": "transport, freight, inland waterways, barge, non-hazardous, foreground",
    "Costs per unit [USD/unit]": 0.0295508274231678,
    "Unit": "tkm",
    "Base Year": 2021,
    "Costs per unit [USD/unit] Reference year": 0.0302358393569228,
    "Reference year": 2023,
    "Costs per unit [USD/unit] Future": 0.0342285506911886,
    "SSP2-Base year": 2035,
    "Identifier": "transport",
    "Years": 0,
    "Description": "This dataset describes the average price per tkm for transportation of a harzdous good by lorry\nAssumption: Transport of containers on an LVZ\nLocation: Sweden\nReference period: 2021\nReference: Panteia",
    "Reference": "van der Meulen et al. 2023",
    "Code": "f59394ab74891208a8122f314a8d6020"
  },
  {
    "Continent": "Europe",
    "Country": "Sweden",
    "City": "not defined",
    "ISO-3166-1 ALPHA-2": "SE",
    "REMIND Region": "EUR",
    "Sector": "Transport",
    "Type": "transport, freight, sea, container ship, hazardous, foreground",
    "Costs per unit [USD/unit]": 0.00173758865248227,
    "Unit": "tkm",
    "Base Year": 2021,
    "Costs per unit [USD/unit] Reference year": 0.00177786735418706,
    "Reference year": 2023,
    "Costs per unit [USD/unit] Future": 0.00201263878064189,
    "SSP2-Base year": 2035,
    "Identifier": "transport",
    "Years": 0,
    "Description": "This dataset describes the average price per tkm for transportation of a harzdous good by lorry\nAssumption: Transport of containers on an LVZ\nLocation: Sweden\nReference period: 2021\nReference: Panteia",
    "Reference": "van der Meulen et al. 2023",
    "Comment": "factor of 5% considered for the transport of hazardous goods",
    "Code": "f59394ab74891208a8122f314a8d6021"
  },
  {
    "Continent": "Europe",
    "Country": "Sweden",
    "City": "not defined",
    "ISO-3166-1 ALPHA-2": "SE",
    "REMIND Region": "EUR",
    "Sector": "Transport",
    "Type": "transport, freight, sea, container ship, non-hazardous, foreground",
    "Costs per unit [USD/unit]": 0.0016548463356974,
    "Unit": "tkm",
    "Base Year": 2021,
    "Costs per unit [USD/unit] Reference year": 0.00169320700398768,
    "Reference year": 2023,
    "Costs per unit [USD/unit] Future": 0.00191679883870656,
    "SSP2-Base year": 2035,
    "Identifier": "transport",
    "Years": 0,
    "Description": "This dataset describes the average price per tkm for transportation of a harzdous good by lorry\nAssumption: Transport of containers on an LVZ\nLocation: Sweden\nReference period: 2021\nReference: Panteia",
    "Reference": "van der Meulen et al. 2023",
    "Code": "f59394ab74891208a8122f314a8d6022"
  },
  {
    "Continent": "Europe",
    "Country": "Sweden",
    "City": "not defined",
    "ISO-3166-1 ALPHA-2": "SE",
    "REMIND Region": "EUR",
    "Sector": "Transport",
    "Type": "transport, freight train, hazardous, foreground",
    "Costs per unit [USD/unit]": 0.0558510638297872,
    "Unit": "tkm",
    "Base Year": 2021,
    "Costs per unit [USD/unit] Reference year": 0.057145736384584,
    "Reference year": 2023,
    "Costs per unit [USD/unit] Future": 0.0646919608063464,
    "SSP2-Base year": 2035,
    "Identifier": "transport",
    "Years": 0,
    "Description": "This dataset describes the average price per tkm for transportation of a harzdous good by lorry\nAssumption: Transport of containers on an LVZ\nLocation: Sweden\nReference period: 2021\nReference: Panteia",
    "Reference": "van der Meulen et al. 2023",
    "Comment": "factor of 5% considered for the transport of hazardous goods",
    "Code": "f59394ab74891208a8122f314a8d6023"
  },
  {
    "Continent": "Europe",
    "Country": "Sweden",
    "City": "not defined",
    "ISO-3166-1 ALPHA-2": "SE",
    "REMIND Region": "EUR",
    "Sector": "Transport",
    "Type": "transport, freight train, non-hazardous, foreground",
    "Costs per unit [USD/unit]": 0.0531914893617021,
    "Unit": "tkm",
    "Base Year": 2021,
    "Costs per unit [USD/unit] Reference year": 0.054424510842461,
    "Reference year": 2023,
    "Costs per unit [USD/unit] Future": 0.0616113912441394,
    "SSP2-Base year": 2035,
    "Identifier": "transport",
    "Years": 0,
    "Description": "This dataset describes the average price per tkm for transportation of a harzdous good by lorry\nAssumption: Transport of containers on an LVZ\nLocation: Sweden\nReference period: 2021\nReference: Panteia",
    "Reference": "van der Meulen et al. 2023",
    "Code": "f59394ab74891208a8122f314a8d6024"
  },
  {
    "Continent": "Asia",
    "Country": "China",
    "City": "not defined",
    "ISO-3166-1 ALPHA-2": "CN",
    "REMIND Region": "CHA",
    "Sector": "Transport",
    "Type": "transport, freight, lorry >32 metric ton, EURO6, hazardous, foreground",
    "Costs per unit [USD/unit]": 0.122872340425532,
    "Unit": "tkm",
    "Base Year": 2021,
    "Costs per unit [USD/unit] Reference year": 0.135370255575143,
    "Reference year": 2023,
    "Costs per unit [USD/unit] Future": 0.174160233327611,
    "SSP2-Base year": 2035,
    "Identifier": "transport",
    "Years": 0,
    "Description": "This dataset describes the average price per tkm for transportation of a harzdous good by lorry\nAssumption: Transport of containers on an LVZ\nLocation: China\nReference period: 2021\nReference: Panteia",
    "Reference": "van der Meulen et al. 2023",
    "Comment": "factor of 5% considered for the transport of hazardous goods",
    "Code": "f59394ab74891208a8122f314a8d6025"
  },
  {
    "Continent": "Asia",
    "Country": "China",
    "City": "not defined",
    "ISO-3166-1 ALPHA-2": "CN",
    "REMIND Region": "CHA",
    "Sector": "Transport",
    "Type": "transport, freight, lorry >32 metric ton, EURO6, non-hazardous, foreground",
    "Costs per unit [USD/unit]": 0.117021276595745,
    "Unit": "tkm",
    "Base Year": 2021,
    "Costs per unit [USD/unit] Reference year": 0.128924052928707,
    "Reference year": 2023,
    "Costs per unit [USD/unit] Future": 0.165866888883439,
    "SSP2-Base year": 2035,
    "Identifier": "transport",
    "Years": 0,
    "Description": "This dataset describes the average price per tkm for transportation of a harzdous good by lorry\nAssumption: Transport of containers on an LVZ\nLocation: China\nReference period: 2021\nReference: Panteia",
    "Reference": "van der Meulen et al. 2023",
    "Code": "f59394ab74891208a8122f314a8d6026"
  },
  {
    "Continent": "Asia",
    "Country": "China",
    "City": "not defined",
    "ISO-3166-1 ALPHA-2": "CN",
    "REMIND Region": "CHA",
    "Sector": "Transport",
    "Type": "transport, freight, inland waterways, barge, hazardous, foreground",
    "Costs per unit [USD/unit]": 0.0310283687943262,
    "Unit": "tkm",
    "Base Year": 2021,
    "Costs per unit [USD/unit] Reference year": 0.0341844079735208,
    "Reference year": 2023,
    "Costs per unit [USD/unit] Future": 0.0439798569009118,
    "SSP2-Base year": 2035,
    "Identifier": "transport",
    "Years": 0,
    "Description": "This dataset describes the average price per tkm for transportation of a harzdous good by lorry\nAssumption: Transport of containers on an LVZ\nLocation: China\nReference period: 2021\nReference: Panteia",
    "Reference": "van der Meulen et al. 2023",
    "Comment": "factor of 5% considered for the transport of hazardous goods",
    "Code": "f59394ab74891208a8122f314a8d6027"
  },
  {
    "Continent": "Asia",
    "Country": "China",
    "City": "not defined",
    "ISO-3166-1 ALPHA-2": "CN",
    "REMIND Region": "CHA",
    "Sector": "Transport",
    "Type": "transport, freight, inland waterways, barge, non-hazardous, foreground",
    "Costs per unit [USD/unit]": 0.0295508274231678,
    "Unit": "tkm",
    "Base Year": 2021,
    "Costs per unit [USD/unit] Reference year": 0.0325565790224008,
    "Reference year": 2023,
    "Costs per unit [USD/unit] Future": 0.0418855780008684,
    "SSP2-Base year": 2035,
    "Identifier": "transport",
    "Years": 0,
    "Description": "This dataset describes the average price per tkm for transportation of a harzdous good by lorry\nAssumption: Transport of containers on an LVZ\nLocation: China\nReference period: 2021\nReference: Panteia",
    "Reference": "van der Meulen et al. 2023",
    "Code": "f59394ab74891208a8122f314a8d6028"
  },
  {
    "Continent": "Asia",
    "Country": "China",
    "City": "not defined",
    "ISO-3166-1 ALPHA-2": "CN",
    "REMIND Region": "CHA",
    "Sector": "Transport",
    "Type": "transport, freight, sea, container ship, hazardous, foreground",
    "Costs per unit [USD/unit]": 0.00173758865248227,
    "Unit": "tkm",
    "Base Year": 2021,
    "Costs per unit [USD/unit] Reference year": 0.00191432684651717,
    "Reference year": 2023,
    "Costs per unit [USD/unit] Future": 0.00246287198645106,
    "SSP2-Base year": 2035,
    "Identifier": "transport",
    "Years": 0,
    "Description": "This dataset describes the average price per tkm for transportation of a harzdous good by lorry\nAssumption: Transport of containers on an LVZ\nLocation: China\nReference period: 2021\nReference: Panteia",
    "Reference": "van der Meulen et al. 2023",
    "Comment": "factor of 5% considered for the transport of hazardous goods",
    "Code": "f59394ab74891208a8122f314a8d6029"
  },
  {
    "Continent": "Asia",
    "Country": "China",
    "City": "not defined",
    "ISO-3166-1 ALPHA-2": "CN",
    "REMIND Region": "CHA",
    "Sector": "Transport",
    "Type": "transport, freight, sea, container ship, non-hazardous, foreground",
    "Costs per unit [USD/unit]": 0.0016548463356974,
    "Unit": "tkm",
    "Base Year": 2021,
    "Costs per unit [USD/unit] Reference year": 0.00182316842525444,
    "Reference year": 2023,
    "Costs per unit [USD/unit] Future": 0.00234559236804863,
    "SSP2-Base year": 2035,
    "Identifier": "transport",
    "Years": 0,
    "Description": "This dataset describes the average price per tkm for transportation of a harzdous good by lorry\nAssumption: Transport of containers on an LVZ\nLocation: China\nReference period: 2021\nReference: Panteia",
    "Reference": "van der Meulen et al. 2023",
    "Code": "f59394ab74891208a8122f314a8d6030"
  },
  {
    "Continent": "Asia",
    "Country": "China",
    "City": "not defined",
    "ISO-3166-1 ALPHA-2": "CN",
    "REMIND Region": "CHA",
    "Sector": "Transport",
    "Type": "transport, freight train, hazardous, foreground",
    "Costs per unit [USD/unit]": 0.0558510638297872,
    "Unit": "tkm",
    "Base Year": 2021,
    "Costs per unit [USD/unit] Reference year": 0.0615319343523375,
    "Reference year": 2023,
    "Costs per unit [USD/unit] Future": 0.0791637424216412,
    "SSP2-Base year": 2035,
    "Identifier": "transport",
    "Years": 0,
    "Description": "This dataset describes the average price per tkm for transportation of a harzdous good by lorry\nAssumption: Transport of containers on an LVZ\nLocation: China\nReference period: 2021\nReference: Panteia",
    "Reference": "van der Meulen et al. 2023",
    "Comment": "factor of 5% considered for the transport of hazardous goods",
    "Code": "f59394ab74891208a8122f314a8d6031"
  },
  {
    "Continent": "Asia",
    "Country": "China",
    "City": "not defined",
    "ISO-3166-1 ALPHA-2": "CN",
    "REMIND Region": "CHA",
    "Sector": "Transport",
    "Type": "transport, freight train, non-hazardous, foreground",
    "Costs per unit [USD/unit]": 0.0531914893617021,
    "Unit": "tkm",
    "Base Year": 2021,
    "Costs per unit [USD/unit] Reference year": 0.0586018422403214,
    "Reference year": 2023,
    "Costs per unit [USD/unit] Future": 0.0753940404015631,
    "SSP2-Base year": 2035,
    "Identifier": "transport",
    "Years": 0,
    "Description": "This dataset describes the average price per tkm for transportation of a harzdous good by lorry\nAssumption: Transport of containers on an LVZ\nLocation: China\nReference period: 2021\nReference: Panteia",
    "Reference": "van der Meulen et al. 2023",
    "Code": "f59394ab74891208a8122f314a8d6032"
  }
]
